bertviz/__init__.py
bertviz/head_view.js
bertviz/head_view.py
bertviz/model_view.js
bertviz/model_view.py
bertviz/neuron_view.js
bertviz/neuron_view.py
bertviz/util.py
bertviz/transformers_neuron_view/__init__.py
bertviz/transformers_neuron_view/file_utils.py
bertviz/transformers_neuron_view/modeling_bert.py
bertviz/transformers_neuron_view/modeling_gpt2.py
bertviz/transformers_neuron_view/modeling_openai.py
bertviz/transformers_neuron_view/modeling_roberta.py
bertviz/transformers_neuron_view/modeling_transfo_xl.py
bertviz/transformers_neuron_view/modeling_transfo_xl_utilities.py
bertviz/transformers_neuron_view/modeling_utils.py
bertviz/transformers_neuron_view/modeling_xlm.py
bertviz/transformers_neuron_view/modeling_xlnet.py
bertviz/transformers_neuron_view/tokenization_bert.py
bertviz/transformers_neuron_view/tokenization_gpt2.py
bertviz/transformers_neuron_view/tokenization_openai.py
bertviz/transformers_neuron_view/tokenization_roberta.py
bertviz/transformers_neuron_view/tokenization_transfo_xl.py
bertviz/transformers_neuron_view/tokenization_utils.py
bertviz/transformers_neuron_view/tokenization_xlm.py
bertviz/transformers_neuron_view/tokenization_xlnet.py
bertviz-1.4.1.dist-info/licenses/LICENSE
bertviz-1.4.1.dist-info/METADATA
bertviz-1.4.1.dist-info/WHEEL
bertviz-1.4.1.dist-info/top_level.txt
bertviz-1.4.1.dist-info/RECORD
