Metadata-Version: 2.4
Name: bertviz
Version: 1.4.1
Summary: Attention visualization tool for NLP Transformer models.
Home-page: https://github.com/jessevig/bertviz
Author: Jesse Vig
License: Apache 2.0
License-File: LICENSE
Requires-Dist: transformers>=2.0
Requires-Dist: torch>=1.0
Requires-Dist: tqdm
Requires-Dist: boto3
Requires-Dist: requests
Requires-Dist: regex
Requires-Dist: sentencepiece
Requires-Dist: IPython>=7.14
Dynamic: author
Dynamic: description
Dynamic: description-content-type
Dynamic: home-page
Dynamic: license
Dynamic: license-file
Dynamic: requires-dist
Dynamic: summary
